{"data":[{"result_type":"restaurants","result_object":{"location_id":"21197116","name":"La Croqueteria de Montrea","latitude":"45.51686","longitude":"-73.59014","num_reviews":"8","timezone":"America/Montreal","location_string":"Montreal, Quebec","photo":{"images":{"small":{"width":"150","url":"https://media-cdn.tripadvisor.com/media/photo-l/1c/41/a2/51/photo0jpg.jpg","height":"150"},"thumbnail":{"width":"50","url":"https://media-cdn.tripadvisor.com/media/photo-t/1c/41/a2/51/photo0jpg.jpg","height":"50"},"original":{"width":"1279","url":"https://media-cdn.tripadvisor.com/media/photo-m/1280/1c/41/a2/51/photo0jpg.jpg","height":"1280"},"large":{"width":"550","url":"https://media-cdn.tripadvisor.com/media/photo-p/1c/41/a2/51/photo0jpg.jpg","height":"550"},"medium":{"width":"450","url":"https://media-cdn.tripadvisor.com/media/photo-s/1c/41/a2/51/photo0jpg.jpg","height":"450"}},"is_blessed":false,"uploaded_date":"2020-10-30T21:01:18-0400","caption":"","id":"474063441","helpful_votes":"0","published_date":"2020-10-30T21:01:18-0400","user":{"user_id":null,"member_id":"0","type":"user"}},"awards":[],"preferred_map_engine":"default","distance":null,"distance_string":null,"bearing":null,"rating":"5.0","is_closed":false,"open_now_text":"Open Now","is_long_closed":false,"description":"","web_url":"","ancestors":[{"subcategory":[{"key":"city","name":"City"}],"name":"Montreal","abbrv":null,"location_id":"155032"},{"subcategory":[{"key":"province","name":"Province"}],"name":"Quebec","abbrv":null,"location_id":"155025"},{"subcategory":[{"key":"country","name":"Country"}],"name":"Canada","abbrv":null,"location_id":"153339"}],"category":{"key":"restaurant","name":"Restaurant"},"subcategory":[],"is_jfy_enabled":false,"nearest_metro_station":[],"address_obj":{"street1":"4520 Avenue Du Parc","street2":null,"city":"Montreal","state":null,"country":"Canada","postalcode":"H2V 4E3"},"address":"4520 Avenue Du Parc, Montreal, Quebec H2V 4E3 Canada","is_candidate_for_contact_info_suppression":false,"cuisine":[{"key":"10655","name":"Spanish"}],"establishment_types":[{"key":"10591","name":"Restaurants"}]},"scope":"local"},{"result_type":"lodging","result_object":{"location_id":"24816738","name":"Le Montreal","latitude":"-32.928627","longitude":"-68.8584","num_reviews":"0","timezone":"America/Argentina/Mendoza","location_string":"Mendoza, Province of Mendoza, Cuyo","awards":[],"preferred_map_engine":"default","distance":null,"distance_string":null,"bearing":null,"is_closed":false,"is_long_closed":false,"special_offers":{"desktop":[],"mobile":[]},"description":"","web_url":"","ancestors":[{"subcategory":[{"key":"municipality","name":"Municipality"}],"name":"Mendoza","abbrv":null,"location_id":"312781"},{"subcategory":[{"key":"province","name":"Province"}],"name":"Province of Mendoza","abbrv":null,"location_id":"312780"},{"subcategory":[{"key":"region","name":"Region"}],"name":"Cuyo","abbrv":null,"location_id":"312777"},{"subcategory":[{"key":"country","name":"Country"}],"name":"Argentina","abbrv":null,"location_id":"294266"}],"category":{"key":"hotel","name":"Hotel"},"subcategory":[{"key":"other","name":"Specialty Lodging"}],"is_jfy_enabled":false,"nearest_metro_station":[],"address_obj":{"street1":"Avenida Dr Tomas Godoy Cruz 567","street2":null,"city":"Mendoza","state":null,"country":"Argentina","postalcode":"M5500GOF"},"address":"Avenida Dr Tomas Godoy Cruz 567, Mendoza M5500GOF Argentina","is_candidate_for_contact_info_suppression":false,"amenities":[]},"scope":"local"},{"result_type":"vacation_rentals","result_object":{"location_id":"24260702","name":"1 bedroom accommodation in Villeneuve-les-Montrea","latitude":"43.18026","longitude":"2.11053","num_reviews":"0","timezone":"Europe/Paris","location_string":"Villeneuve Les Montreal, Montreal, Aude, Occitanie","photo":{"images":{"small":{"width":"320","url":"https://media-cdn.tripadvisor.com/media/vr-ha-splice-l/0f/e0/32/ec.jpg","height":"240"},"thumbnail":{"width":"148","url":"https://media-cdn.tripadvisor.com/media/vr-ha-splice-m/0f/e0/32/ec.jpg","height":"111"},"original":{"width":"320","url":"https://media-cdn.tripadvisor.com/media/vr-ha-splice-l/0f/e0/32/ec.jpg","height":"240"},"large":{"width":"320","url":"https://media-cdn.tripadvisor.com/media/vr-ha-splice-l/0f/e0/32/ec.jpg","height":"240"},"medium":{"width":"320","url":"https://media-cdn.tripadvisor.com/media/vr-ha-splice-l/0f/e0/32/ec.jpg","height":"240"}},"is_blessed":false,"uploaded_date":null,"caption":"","id":"0","helpful_votes":"0","published_date":null,"user":null},"awards":[],"doubleclick_zone":"eu.france.languedoc_roussillon.aude","distance":null,"distance_string":null,"bearing":null,"is_closed":false,"is_long_closed":false,"description":"","web_url":"","ancestors":[{"subcategory":[{"key":"city","name":"City"}],"name":"Villeneuve Les Montreal","abbrv":null,"location_id":"2137465"},{"subcategory":[{"key":"municipality","name":"Municipality"}],"name":"Montreal","abbrv":null,"location_id":"1726266"},{"subcategory":[{"key":"department","name":"Department"}],"name":"Aude","abbrv":null,"location_id":"2462549"},{"subcategory":[{"key":"region","name":"Region"}],"name":"Occitanie","abbrv":null,"location_id":"11038881"},{"subcategory":[{"key":"country","name":"Country"}],"name":"France","abbrv":null,"location_id":"187070"}],"category":{"key":"vacationrental","name":"Vacation Rentals"},"subcategory":[{"key":"vr","name":"vacation rentals"}],"guide_count":"0","is_jfy_enabled":false,"nearest_metro_station":[],"address":"Villeneuve Les Montreal, France","is_candidate_for_contact_info_suppression":false},"scope":"local"},{"result_type":"vacation_rentals","result_object":{"location_id":"24480843","name":"Walkable Neighborhood Near Old Port, Close to Old Port of Montrea","latitude":"45.510757","longitude":"-73.56065","num_reviews":"0","timezone":"America/Montreal","location_string":"Montreal, Quebec","photo":{"images":{"small":{"width":"320","url":"https://media-cdn.tripadvisor.com/media/vr-ha-splice-l/0e/cf/47/90.jpg","height":"240"},"thumbnail":{"width":"148","url":"https://media-cdn.tripadvisor.com/media/vr-ha-splice-m/0e/cf/47/90.jpg","height":"111"},"original":{"width":"320","url":"https://media-cdn.tripadvisor.com/media/vr-ha-splice-l/0e/cf/47/90.jpg","height":"240"},"large":{"width":"320","url":"https://media-cdn.tripadvisor.com/media/vr-ha-splice-l/0e/cf/47/90.jpg","height":"240"},"medium":{"width":"320","url":"https://media-cdn.tripadvisor.com/media/vr-ha-splice-l/0e/cf/47/90.jpg","height":"240"}},"is_blessed":false,"uploaded_date":null,"caption":"","id":"0","helpful_votes":"0","published_date":null,"user":null},"awards":[],"doubleclick_zone":"na.can.quebec.montreal","distance":null,"distance_string":null,"bearing":null,"is_closed":false,"is_long_closed":false,"description":"","web_url":"","ancestors":[{"subcategory":[{"key":"city","name":"City"}],"name":"Montreal","abbrv":null,"location_id":"155032"},{"subcategory":[{"key":"province","name":"Province"}],"name":"Quebec","abbrv":null,"location_id":"155025"},{"subcategory":[{"key":"country","name":"Country"}],"name":"Canada","abbrv":null,"location_id":"153339"}],"category":{"key":"vacationrental","name":"Vacation Rentals"},"subcategory":[{"key":"vr","name":"vacation rentals"}],"guide_count":"0","is_jfy_enabled":false,"nearest_metro_station":[],"address":"Montreal, Quebec","is_candidate_for_contact_info_suppression":false},"scope":"local"}],"metadata":{"scope":"local"},"sort":[{"filter_key":"relevance","label":"Relevance","locale_independent_label":"relevance","selected":true},{"filter_key":"distance","label":"Distance","locale_independent_label":"distance","selected":false}],"partial_content":false,"tracking":{"search_id":"5CFF6A794F7947EA982016CD7C72637F1680970682636"},"paging":{"results":"4","total_results":"4"}}